modules/__init__.py
modules/executor/__init__.py
modules/executor/executor.py
modules/executor/bridge/__init__.py
modules/executor/bridge/base_bridge.py
modules/executor/bridge/executor_bridge.py
modules/executor/bridge/cpp/__init__.py
modules/executor/bridge/cpp/create_bridge.py
modules/executor/bridge/cpp/destroy_bridge.py
modules/executor/bridge/cpp/history_bridge.py
modules/executor/bridge/cpp/info_bridge.py
modules/executor/bridge/cpp/list_bridge.py
modules/executor/bridge/cpp/start_bridge.py
modules/executor/bridge/cpp/stop_bridge.py
modules/executor/bridge/cpp/version_bridge.py
modules/executor/dto/__init__.py
modules/executor/dto/config.py
modules/executor/dto/options.py
modules/executor/dto/pipeline.py
modules/executor/dto/responses.py
modules/executor/services/__init__.py
modules/executor/services/create_service.py
modules/executor/services/destroy_service.py
modules/executor/services/history_service.py
modules/executor/services/info_service.py
modules/executor/services/list_service.py
modules/executor/services/start_service.py
modules/executor/services/stop_service.py
modules/executor/services/version_service.py
modules/executor/utils/unified_logging.py
modules/operator_registry/__init__.py
modules/operator_registry/operator_registry.py
modules/operator_registry/bridge/__init__.py
modules/operator_registry/bridge/operator_registry_bridge.py
modules/operator_registry/bridge/cpp/__init__.py
modules/operator_registry/bridge/cpp/free_bridge.py
modules/operator_registry/bridge/cpp/info_bridge.py
modules/operator_registry/bridge/cpp/install_bridge.py
modules/operator_registry/bridge/cpp/list_bridge.py
modules/operator_registry/bridge/cpp/push_bridge.py
modules/operator_registry/bridge/cpp/uninstall_bridge.py
modules/operator_registry/config/__init__.py
modules/operator_registry/config/config.py
modules/operator_registry/dto/__init__.py
modules/operator_registry/dto/operator.py
modules/operator_registry/dto/operator_info.py
nexstem_registry_stack-1.0.0.dist-info/licenses/LICENSE
nexstem_registry_stack-1.0.0.dist-info/METADATA
nexstem_registry_stack-1.0.0.dist-info/WHEEL
nexstem_registry_stack-1.0.0.dist-info/entry_points.txt
nexstem_registry_stack-1.0.0.dist-info/top_level.txt
nexstem_registry_stack-1.0.0.dist-info/RECORD
