Metadata-Version: 2.4
Name: nexstem-registry-stack
Version: 1.0.0
Summary: Python SDK for SW Registry Stack - Operator Registry, Pipeline Registry, Executor, and Recorder
Home-page: https://github.com/sw-registry-stack/sdk
Author: Vignesh Sambari
Author-email: Vignesh Sambari <vignesh.sambari@nexstem.ai>
Maintainer-email: Vignesh Sambari <vignesh.sambari@nexstem.ai>
License: MIT
Project-URL: Homepage, https://github.com/sw-registry-stack/sdk
Project-URL: Documentation, https://sw-registry-stack.readthedocs.io/
Project-URL: Repository, https://github.com/sw-registry-stack/sdk.git
Project-URL: Bug Tracker, https://github.com/sw-registry-stack/sdk/issues
Keywords: sw-registry-stack,operator-registry,pipeline-registry,executor,recorder,cffi,python,sdk
Classifier: Development Status :: 5 - Production/Stable
Classifier: Intended Audience :: Developers
Classifier: License :: OSI Approved :: MIT License
Classifier: Operating System :: OS Independent
Classifier: Programming Language :: Python :: 3
Classifier: Programming Language :: Python :: 3.8
Classifier: Programming Language :: Python :: 3.9
Classifier: Programming Language :: Python :: 3.10
Classifier: Programming Language :: Python :: 3.11
Classifier: Programming Language :: Python :: 3.12
Classifier: Topic :: Software Development :: Libraries :: Python Modules
Classifier: Topic :: System :: Systems Administration
Requires-Python: >=3.8
License-File: LICENSE
Requires-Dist: cffi>=1.15.0
Requires-Dist: pydantic>=2.0.0
Requires-Dist: typing-extensions>=4.0.0
Provides-Extra: dev
Requires-Dist: pytest>=7.0.0; extra == "dev"
Requires-Dist: pytest-asyncio>=0.21.0; extra == "dev"
Requires-Dist: pytest-cov>=4.0.0; extra == "dev"
Requires-Dist: black>=23.0.0; extra == "dev"
Requires-Dist: isort>=5.12.0; extra == "dev"
Requires-Dist: mypy>=1.0.0; extra == "dev"
Requires-Dist: flake8>=6.0.0; extra == "dev"
Requires-Dist: pre-commit>=3.0.0; extra == "dev"
Provides-Extra: docs
Requires-Dist: sphinx>=6.0.0; extra == "docs"
Requires-Dist: sphinx-rtd-theme>=1.2.0; extra == "docs"
Requires-Dist: myst-parser>=1.0.0; extra == "docs"
Provides-Extra: test
Requires-Dist: pytest>=7.0.0; extra == "test"
Requires-Dist: pytest-asyncio>=0.21.0; extra == "test"
Requires-Dist: pytest-cov>=4.0.0; extra == "test"
Requires-Dist: pytest-mock>=3.10.0; extra == "test"
Dynamic: author
Dynamic: home-page
Dynamic: license-file
Dynamic: requires-python
